pyregbl/__init__.py
pyregbl/attributes.py
pyregbl/client.py
pyregbl/mapping_table.py
pyregbl/response.py
pyregbl/utils.py
pyregbl/.ipynb_checkpoints/main-checkpoint.py
pyregbl/tables/GBAUP.py
pyregbl/tables/GENH.py
pyregbl/tables/GENW.py
pyregbl/tables/GKAT.py
pyregbl/tables/GKLAS.py
pyregbl/tables/GKSCE.py
pyregbl/tables/GSTAT.py
pyregbl/tables/GVOLNORM.py
pyregbl/tables/GVOLSCE.py
pyregbl/tables/GWAERSCEH.py
pyregbl/tables/GWAERSCEW.py
pyregbl/tables/GWAERZH.py
pyregbl/tables/GWAERZW.py
pyregbl/tables/LTYP.py
pyregbl/tables/PARTAB.py
pyregbl/tables/PARTBZ.py
pyregbl/tables/PSTAT.py
pyregbl/tables/PTYPAG.py
pyregbl/tables/PTYPBW.py
pyregbl/tables/SREAL.py
pyregbl/tables/STRART.py
pyregbl/tables/STRSP.py
pyregbl/tables/WGBANMERKUNG.py
pyregbl/tables/WNART.py
pyregbl/tables/WNARTSCE.py
pyregbl/tables/WSTAT.py
pyregbl/tables/__init__.py
pyregbl-0.3.0.dist-info/METADATA
pyregbl-0.3.0.dist-info/WHEEL
pyregbl-0.3.0.dist-info/licenses/LICENSE
pyregbl-0.3.0.dist-info/RECORD
