Metadata-Version: 2.3
Name: PyRegBL
Version: 0.3.0
Summary: Reaserch tool to query RegBL data in Python
Author-email: Fred Montet <fredmontet@gmail.com>
License-File: LICENSE
Requires-Python: >=3.8
Requires-Dist: requests>=2.32.3
Requires-Dist: slumber>=0.7.1
